{
  "response": {
    "data": [
      {
        "countryName": "Myanmar",
        "countryCode1": "M",
        "countryCode2": "MMR",
        "countryFlag": "MM.png",
        "capital": "",
        "currencyCode": "MMK",
        "currencyName": "Kyat",
        "currencySymbol": "K",
        "capitalLatitude": null,
        "capitalLongitude": null,
        "isoNumeric": 104
      },
      {
        "countryName": "U.S. Virgin Island",
        "countryCode1": "VI",
        "countryCode2": "VIR",
        "countryFlag": "VI.png",
        "capital": "",
        "currencyCode": "USD",
        "currencyName": "Dollar",
        "currencySymbol": "$",
        "capitalLatitude": null,
        "capitalLongitude": null,
        "isoNumeric": 850
      },
      {
        "countryName": "Latvia",
        "countryCode1": "LV",
        "countryCode2": "LVA",
        "countryFlag": "LV.png",
        "capital": "",
        "currencyCode": "LVL",
        "currencyName": "Lat",
        "currencySymbol": "Ls",
        "capitalLatitude": null,
        "capitalLongitude": null,
        "isoNumeric": 428
      },
      {
        "countryName": "British Indian Ocean Teritory",
        "countryCode1": "IO",
        "countryCode2": "IOT",
        "countryFlag": "IO.png",
        "capital": "",
        "currencyCode": "USD",
        "currencyName": "Dollar",
        "currencySymbol": "$",
        "capitalLatitude": null,
        "capitalLongitude": null,
        "isoNumeric": 86
      },
      {
        "countryName": "Reunion",
        "countryCode1": "RE",
        "countryCode2": "REU",
        "countryFlag": "RE.png",
        "capital": "",
        "currencyCode": "EUR",
        "currencyName": "Euro",
        "currencySymbol": "€",
        "capitalLatitude": null,
        "capitalLongitude": null,
        "isoNumeric": 638
      },
      {
        "countryName": "Gabon",
        "countryCode1": "GA",
        "countryCode2": "GAB",
        "countryFlag": "GA.png",
        "capital": "",
        "currencyCode": "XAF",
        "currencyName": "Franc",
        "currencySymbol": "FCF",
        "capitalLatitude": null,
        "capitalLongitude": null,
        "isoNumeric": 266
      },
      {
        "countryName": "Guyana",
        "countryCode1": "GY",
        "countryCode2": "GUY",
        "countryFlag": "GY.png",
        "capital": "",
        "currencyCode": "GYD",
        "currencyName": "Dollar",
        "currencySymbol": "$",
        "capitalLatitude": null,
        "capitalLongitude": null,
        "isoNumeric": 328
      },
      {
        "countryName": "Tajikistan",
        "countryCode1": "TJ",
        "countryCode2": "TJK",
        "countryFlag": "TJ.png",
        "capital": "",
        "currencyCode": "TJS",
        "currencyName": "Somoni",
        "currencySymbol": "",
        "capitalLatitude": null,
        "capitalLongitude": null,
        "isoNumeric": 762
      },
      {
        "countryName": "Slovenia",
        "countryCode1": "SI",
        "countryCode2": "SVN",
        "countryFlag": "SI.png",
        "capital": "",
        "currencyCode": "EUR",
        "currencyName": "Euro",
        "currencySymbol": "€",
        "capitalLatitude": null,
        "capitalLongitude": null,
        "isoNumeric": 705
      },
      {
        "countryName": "Martinique",
        "countryCode1": "MQ",
        "countryCode2": "MTQ",
        "countryFlag": "MQ.png",
        "capital": "",
        "currencyCode": "EUR",
        "currencyName": "Euro",
        "currencySymbol": "€",
        "capitalLatitude": null,
        "capitalLongitude": null,
        "isoNumeric": 474
      },
      {
        "countryName": "Puerto Rico",
        "countryCode1": "PR",
        "countryCode2": "PRI",
        "countryFlag": "PR.png",
        "capital": "",
        "currencyCode": "USD",
        "currencyName": "Dollar",
        "currencySymbol": "$",
        "capitalLatitude": null,
        "capitalLongitude": null,
        "isoNumeric": 630
      },
      {
        "countryName": "Niger",
        "countryCode1": "NE",
        "countryCode2": "NER",
        "countryFlag": "NE.png",
        "capital": "",
        "currencyCode": "XOF",
        "currencyName": "Franc",
        "currencySymbol": "",
        "capitalLatitude": null,
        "capitalLongitude": null,
        "isoNumeric": 562
      },
      {
        "countryName": "Faroe Islands",
        "countryCode1": "FO",
        "countryCode2": "FRO",
        "countryFlag": "FO.png",
        "capital": "",
        "currencyCode": "DKK",
        "currencyName": "Krone",
        "currencySymbol": "kr",
        "capitalLatitude": null,
        "capitalLongitude": null,
        "isoNumeric": 234
      },
      {
        "countryName": "Reunion",
        "countryCode1": "RE",
        "countryCode2": "REU",
        "countryFlag": "RE.png",
        "capital": "",
        "currencyCode": null,
        "currencyName": "Dinar",
        "currencySymbol": null,
        "capitalLatitude": null,
        "capitalLongitude": null,
        "isoNumeric": 0
      },
      {
        "countryName": "Hong Kong",
        "countryCode1": "HK",
        "countryCode2": "HKG",
        "countryFlag": "HK.png",
        "capital": "",
        "currencyCode": "HKD",
        "currencyName": "Dollar",
        "currencySymbol": "$",
        "capitalLatitude": null,
        "capitalLongitude": null,
        "isoNumeric": 344
      },
      {
        "countryName": "Bhutan",
        "countryCode1": "BT",
        "countryCode2": "BTN",
        "countryFlag": "BT.png",
        "capital": "",
        "currencyCode": "BTN",
        "currencyName": "Ngultrum",
        "currencySymbol": "",
        "capitalLatitude": null,
        "capitalLongitude": null,
        "isoNumeric": 64
      },
      {
        "countryName": "Tokelau",
        "countryCode1": "TK",
        "countryCode2": "TKL",
        "countryFlag": "TK.png",
        "capital": "",
        "currencyCode": "NZD",
        "currencyName": "Dollar",
        "currencySymbol": "$",
        "capitalLatitude": null,
        "capitalLongitude": null,
        "isoNumeric": 772
      },
      {
        "countryName": "Bahrain",
        "countryCode1": "BH",
        "countryCode2": "BHR",
        "countryFlag": "BH.png",
        "capital": "",
        "currencyCode": "BHD",
        "currencyName": "Dinar",
        "currencySymbol": "",
        "capitalLatitude": null,
        "capitalLongitude": null,
        "isoNumeric": 48
      },
      {
        "countryName": "Tonga",
        "countryCode1": "TO",
        "countryCode2": "TON",
        "countryFlag": "TO.png",
        "capital": "",
        "currencyCode": "TOP",
        "currencyName": "Paanga",
        "currencySymbol": "T$",
        "capitalLatitude": null,
        "capitalLongitude": null,
        "isoNumeric": 776
      },
      {
        "countryName": "El Salvador",
        "countryCode1": "SV",
        "countryCode2": "SLV",
        "countryFlag": "SV.png",
        "capital": "",
        "currencyCode": "SVC",
        "currencyName": "Colone",
        "currencySymbol": "$",
        "capitalLatitude": null,
        "capitalLongitude": null,
        "isoNumeric": 222
      },
      {
        "countryName": "Uruguay",
        "countryCode1": "UY",
        "countryCode2": "URY",
        "countryFlag": "UY.png",
        "capital": "",
        "currencyCode": "UYU",
        "currencyName": "Peso",
        "currencySymbol": "$U",
        "capitalLatitude": null,
        "capitalLongitude": null,
        "isoNumeric": 858
      },
      {
        "countryName": "Jamaica",
        "countryCode1": "JM",
        "countryCode2": "JAM",
        "countryFlag": "JM.png",
        "capital": "",
        "currencyCode": "JMD",
        "currencyName": "Dollar",
        "currencySymbol": "$",
        "capitalLatitude": null,
        "capitalLongitude": null,
        "isoNumeric": 388
      },
      {
        "countryName": "Libya",
        "countryCode1": "LY",
        "countryCode2": "LBY",
        "countryFlag": "LY.png",
        "capital": "",
        "currencyCode": "LYD",
        "currencyName": "Dinar",
        "currencySymbol": "",
        "capitalLatitude": null,
        "capitalLongitude": null,
        "isoNumeric": 434
      },
      {
        "countryName": "Bolivia",
        "countryCode1": "BO",
        "countryCode2": "BOL",
        "countryFlag": "BO.png",
        "capital": "",
        "currencyCode": "BOB",
        "currencyName": "Boliviano",
        "currencySymbol": "$b",
        "capitalLatitude": null,
        "capitalLongitude": null,
        "isoNumeric": 68
      },
      {
        "countryName": "Grenada",
        "countryCode1": "GD",
        "countryCode2": "GRD",
        "countryFlag": "GD.png",
        "capital": "",
        "currencyCode": "XCD",
        "currencyName": "Dollar",
        "currencySymbol": "$",
        "capitalLatitude": null,
        "capitalLongitude": null,
        "isoNumeric": 308
      },
      {
        "countryName": "French Guiana",
        "countryCode1": "GF",
        "countryCode2": "GUF",
        "countryFlag": "GF.png",
        "capital": "",
        "currencyCode": "EUR",
        "currencyName": "Euro",
        "currencySymbol": "€",
        "capitalLatitude": null,
        "capitalLongitude": null,
        "isoNumeric": 254
      },
      {
        "countryName": "Jordan",
        "countryCode1": "JO",
        "countryCode2": "JOR",
        "countryFlag": "JO.png",
        "capital": "",
        "currencyCode": "JOD",
        "currencyName": "Dinar",
        "currencySymbol": "",
        "capitalLatitude": null,
        "capitalLongitude": null,
        "isoNumeric": 400
      }
    ]
  }
}
